mailinator/__init__.py
mailinator/mailinator.py
mailinatorapi/__init__.py
mailinatorapi/mailinator.py
mailinator_public_api-0.1.1.dist-info/LICENSE
mailinator_public_api-0.1.1.dist-info/METADATA
mailinator_public_api-0.1.1.dist-info/WHEEL
mailinator_public_api-0.1.1.dist-info/top_level.txt
mailinator_public_api-0.1.1.dist-info/RECORD
