Metadata-Version: 2.1
Name: mailinator-public-api
Version: 0.1.1
Summary: A simple python wrapper for the Public mailinator websockets API
Home-page: https://github.com/matheusfillipe/mailinator
Author: Matheus Fillipe
Author-email: mattf@tilde.club
License: UNKNOWN
Platform: UNKNOWN
Classifier: Development Status :: 5 - Production/Stable
Classifier: Programming Language :: Python :: 3
Classifier: License :: OSI Approved :: MIT License
Classifier: Operating System :: OS Independent
Classifier: Topic :: Software Development :: Libraries :: Python Modules
Classifier: Topic :: Communications
Classifier: Topic :: Internet
Requires-Python: >=3.7
License-File: LICENSE
Requires-Dist: certifi (==2021.10.8)
Requires-Dist: charset-normalizer (==2.0.10)
Requires-Dist: idna (==3.3)
Requires-Dist: requests (==2.27.1)
Requires-Dist: urllib3 (==1.26.8)
Requires-Dist: websockets (==10.1)
